LICENSE
pytest_collector/__init__.py
pytest_collector/__main__.py
pytest_collector/collector.py
pytest_collector-0.1.0.dist-info/LICENSE
pytest_collector-0.1.0.dist-info/WHEEL
pytest_collector-0.1.0.dist-info/METADATA
pytest_collector-0.1.0.dist-info/RECORD
